{
    "printDate": "2024-03-04",
    "id": 7,
    "editor": "Heidi Erwin",
    "spangram": "PUNCTUATION",
    "clue": "Mark my words",
    "startingBoard": [
        "PERPON",
        "DOIULS",
        "OMANOL",
        "CMCACA",
        "UTHPOS",
        "NAEPSH",
        "EPTORT",
        "HYHION"
    ],
    "solutions": [
        "PERIOD",
        "COMMA",
        "COLON",
        "APOSTROPHE",
        "HYPHEN",
        "SLASH",
        "PUNCTUATION",
        "ACAI",
        "ACHE",
        "ACTA",
        "ACTUATE",
        "ACTUATION",
        "ACTUATOR",
        "ACTUATORS",
        "AHEAP",
        "AIRED",
        "ALCO",
        "ALCOS",
        "ALLONS",
        "ALLS",
        "ALLURE",
        "ALLURED",
        "ALSO",
        "AMIE",
        "AMIN",
        "AMINO",
        "AMIR",
        "AMMINO",
        "AMMO",
        "AMORINO",
        "ANIMA",
        "ANOA",
        "ANOAS",
        "ANTE",
        "ANTETYPE",
        "ANURIA",
        "APOS",
        "APPORT",
        "APPORTS",
        "APPRO",
        "APPROS",
        "APPS",
        "APSO",
        "APSOS",
        "ASSORT",
        "ASSOT",
        "ATHIRST",
        "ATMA",
        "ATMAN",
        "ATOP",
        "AULOS",
        "AUNE",
        "AUNT",
        "AUREI",
        "CACA",
        "CACAO",
        "CACAOS",
        "CACAS",
        "CACHE",
        "CACHEPOT",
        "CACHET",
        "CAIN",
        "CALL",
        "CALLOP",
        "CALLS",
        "CALLUNA",
        "CALO",
        "CALOS",
        "CAMMIE",
        "CAMO",
        "CANAPE",
        "CANCHA",
        "CANIER",
        "CANOLA",
        "CANOLAS",
        "CAPE",
        "CAPH",
        "CAPO",
        "CAPOS",
        "CAPS",
        "CASH",
        "CAUL",
        "CAULS",
        "CAUP",
        "CHACO",
        "CHACOS",
        "CHANT",
        "CHAO",
        "CHAOS",
        "CHAP",
        "CHAPE",
        "CHAPEAU",
        "CHAPS",
        "CHAPT",
        "CHAT",
        "CHAUNT",
        "CHEAP",
        "CHEAPEN",
        "CHEAPY",
        "CHEAT",
        "CHETH",
        "CLASH",
        "CLASS",
        "CLOACA",
        "CLON",
        "CLOU",
        "CLOUR",
        "CLOURED",
        "COACH",
        "COACHMAN",
        "COACT",
        "COAL",
        "COALS",
        "CODE",
        "CODEIA",
        "CODEIN",
        "CODEINA",
        "CODER",
        "CODOMAIN",
        "COLA",
        "COLAS",
        "COLL",
        "COLLOP",
        "COLLS",
        "COLONS",
        "COLOUR",
        "COLOURED",
        "COLS",
        "COLURE",
        "COMA",
        "COMM",
        "COMMIE",
        "COMMO",
        "COMMODE",
        "COMMUNE",
        "COMMUTATE",
        "COMMUTATION",
        "COMMUTATOR",
        "COMMUTATORS",
        "COMMUTE",
        "COMTE",
        "CONCH",
        "CONCHA",
        "CONCHAE",
        "CONCHATE",
        "CONCHE",
        "CONI",
        "CONIA",
        "CONIMA",
        "CONURE",
        "COOED",
        "COOER",
        "COOM",
        "COOMIER",
        "COOP",
        "COOPED",
        "COOPER",
        "COORIE",
        "COORIED",
        "COPE",
        "COPS",
        "COSH",
        "COSS",
        "COST",
        "COUP",
        "COUPON",
        "COUPONS",
        "COUR",
        "COURE",
        "COURED",
        "COURIE",
        "COURIED",
        "CUMMIN",
        "CUNEATE",
        "CUTCH",
        "CUTCHA",
        "CUTE",
        "DERO",
        "DOER",
        "DOMAIN",
        "DOMIER",
        "DOMINO",
        "DOMINOS",
        "DOOM",
        "DOOMIER",
        "DOOR",
        "DOPE",
        "DOPER",
        "DORE",
        "DORP",
        "EATCHE",
        "EATH",
        "EATHE",
        "EINA",
        "ENATE",
        "ENATION",
        "EOAN",
        "EPACT",
        "EPHA",
        "EPHOR",
        "EPHORI",
        "EPHORS",
        "EPOPT",
        "EPOS",
        "ERIACH",
        "ETAPE",
        "ETAT",
        "ETCH",
        "ETHANE",
        "ETHANOL",
        "ETHANOLS",
        "ETHION",
        "ETHIOPS",
        "ETHOS",
        "ETNA",
        "HAEN",
        "HAET",
        "HANT",
        "HANUMAN",
        "HAPS",
        "HATE",
        "HATH",
        "HAUNT",
        "HAUT",
        "HAUTE",
        "HEAP",
        "HEAPY",
        "HEAT",
        "HEATH",
        "HEATHY",
        "HENT",
        "HEPS",
        "HEPT",
        "HEPTANE",
        "HETH",
        "HETMAN",
        "HOAS",
        "HOON",
        "HOOT",
        "HOOTS",
        "HOPE",
        "HOPS",
        "HORI",
        "HORN",
        "HORS",
        "HORST",
        "HOSS",
        "HOST",
        "HOTE",
        "HYEN",
        "HYENA",
        "HYPATE",
        "HYPE",
        "HYPHENATE",
        "HYPHENATION",
        "HYPNUM",
        "HYTE",
        "IMAM",
        "IMMUNE",
        "INCH",
        "INURE",
        "INURED",
        "IOTA",
        "IRED",
        "IRON",
        "IURE",
        "LACS",
        "LASH",
        "LASS",
        "LASSO",
        "LOACH",
        "LOAN",
        "LOCA",
        "LOCAL",
        "LOCALS",
        "LOCO",
        "LOCOS",
        "LOUIE",
        "LOUN",
        "LOUP",
        "LOUR",
        "LOURE",
        "LOURED",
        "LOURIE",
        "LUACH",
        "LUNA",
        "LUNCH",
        "LUNIER",
        "LUPIN",
        "LURE",
        "LURED",
        "MACACO",
        "MACACOS",
        "MACH",
        "MACHAN",
        "MACHE",
        "MACTATION",
        "MAIM",
        "MAIN",
        "MAINOUR",
        "MAIR",
        "MAIRE",
        "MAMIE",
        "MANA",
        "MANCHE",
        "MANCHET",
        "MANI",
        "MANO",
        "MANOAO",
        "MANOAOS",
        "MANOS",
        "MANUL",
        "MANULS",
        "MANURE",
        "MANURED",
        "MAUL",
        "MAULS",
        "MAUN",
        "MAURI",
        "MIAUL",
        "MIAULS",
        "MINA",
        "MINO",
        "MINOS",
        "MIRE",
        "MIRED",
        "MIRO",
        "MOAI",
        "MOAN",
        "MODE",
        "MODER",
        "MOER",
        "MOIRE",
        "MOMI",
        "MOOD",
        "MOOED",
        "MOOI",
        "MOOP",
        "MOOPED",
        "MOOR",
        "MOORED",
        "MOPE",
        "MOPED",
        "MOPER",
        "MORE",
        "MORIA",
        "MUNT",
        "MUTATE",
        "MUTATION",
        "MUTCH",
        "MUTE",
        "MUTHA",
        "NAAM",
        "NACH",
        "NACHE",
        "NAIRU",
        "NAMU",
        "NAOI",
        "NAOS",
        "NAPE",
        "NAPPE",
        "NAPS",
        "NATCH",
        "NATION",
        "NAUTCH",
        "NEAP",
        "NEAT",
        "NEATH",
        "NEPETA",
        "NIED",
        "NOAH",
        "NOIR",
        "NOIRS",
        "NOLL",
        "NOLLS",
        "NOLO",
        "NOLOS",
        "NOOIT",
        "NOOP",
        "NOOPS",
        "NORI",
        "NORITE",
        "NORTH",
        "NORTHS",
        "NOUL",
        "NOULS",
        "NOUN",
        "NOUNIER",
        "NOUP",
        "NULL",
        "NULLA",
        "NULLAS",
        "NULLS",
        "NUTATE",
        "NUTATION",
        "OCAS",
        "OCTA",
        "OCTAN",
        "OCTANE",
        "OCTET",
        "ODOR",
        "OLLA",
        "OLLAS",
        "ONCOST",
        "ONIE",
        "OOMIAC",
        "OONT",
        "OONTS",
        "OOPED",
        "OOPS",
        "OORIE",
        "OOTS",
        "OPAH",
        "OPED",
        "OPEPE",
        "OPPO",
        "OPPOS",
        "OPTANT",
        "OPTION",
        "ORPHAN",
        "ORPIN",
        "ORTHO",
        "ORTHOS",
        "ORTS",
        "OSSA",
        "OURIE",
        "PACA",
        "PACAS",
        "PACHA",
        "PACO",
        "PACOS",
        "PACS",
        "PACT",
        "PACTA",
        "PACTUM",
        "PANACHE",
        "PANE",
        "PANIER",
        "PANIM",
        "PANT",
        "PAOLO",
        "PATCH",
        "PATE",
        "PATH",
        "PATHOS",
        "PATIO",
        "PATIOS",
        "PATU",
        "PATY",
        "PEAN",
        "PEANUT",
        "PEAT",
        "PEATMAN",
        "PEATY",
        "PEIN",
        "PEINCT",
        "PENT",
        "PEPO",
        "PEPOS",
        "PEPS",
        "PERI",
        "PERP",
        "PETNAP",
        "PHAT",
        "PHENATE",
        "PHOS",
        "PHOSPHATE",
        "PHOT",
        "PHYTANE",
        "PIAN",
        "PIANO",
        "PIANOS",
        "PIED",
        "PIER",
        "PIMA",
        "PINA",
        "PINCH",
        "POACH",
        "POAS",
        "POCO",
        "POCOSON",
        "POEP",
        "POEPS",
        "POET",
        "POLL",
        "POLLS",
        "POLO",
        "POLONIE",
        "POLOS",
        "POLS",
        "POMO",
        "PONS",
        "POOD",
        "POON",
        "POOR",
        "POORI",
        "POORT",
        "POORTS",
        "POOT",
        "POOTS",
        "POPE",
        "POPS",
        "PORE",
        "PORED",
        "PORINA",
        "PORN",
        "PORNO",
        "PORT",
        "PORTHOS",
        "PORTS",
        "POSH",
        "POSHO",
        "POSHOS",
        "POSS",
        "POST",
        "POSTRIOT",
        "POTAE",
        "POTE",
        "POTION",
        "POUR",
        "POURED",
        "POURIE",
        "PREDOOM",
        "PREOP",
        "PREP",
        "PRIED",
        "PRIM",
        "PRIMA",
        "PRIMO",
        "PRION",
        "PROA",
        "PROD",
        "PROIN",
        "PROM",
        "PROMO",
        "PROO",
        "PROP",
        "PROS",
        "PROSO",
        "PROSOS",
        "PROSS",
        "PROST",
        "PROTEA",
        "PROTEAN",
        "PRUINA",
        "PSOAS",
        "PUIR",
        "PULL",
        "PULLS",
        "PULS",
        "PUNA",
        "PUNCH",
        "PUNCTA",
        "PUNCTATE",
        "PUNCTATION",
        "PUNCTATOR",
        "PUNCTATORS",
        "PUNCTUATE",
        "PUNCTUATOR",
        "PUNCTUATORS",
        "PUNCTUM",
        "PUNIER",
        "PURE",
        "PURED",
        "PURI",
        "PURIM",
        "PURIN",
        "REDO",
        "REIN",
        "REPO",
        "REPOMAN",
        "RHOS",
        "RIMA",
        "RIOT",
        "RIOTS",
        "RITE",
        "ROACH",
        "ROAM",
        "ROAN",
        "RODE",
        "RODMAN",
        "ROED",
        "ROIN",
        "ROMA",
        "ROMAN",
        "ROMANO",
        "ROMANOS",
        "ROMCOM",
        "RONT",
        "RONTS",
        "ROOD",
        "ROOM",
        "ROOMIE",
        "ROON",
        "ROOP",
        "ROOPS",
        "ROOS",
        "ROOST",
        "ROOT",
        "ROOTS",
        "ROOTY",
        "ROPE",
        "ROPED",
        "ROST",
        "ROTA",
        "ROTAN",
        "ROTATE",
        "ROTE",
        "ROTI",
        "ROTS",
        "RUANA",
        "RUIN",
        "RUNCH",
        "RUPIA",
        "SALL",
        "SALOL",
        "SALOLS",
        "SALON",
        "SALS",
        "SCALL",
        "SCALLOP",
        "SCALLS",
        "SCAN",
        "SCAPE",
        "SCOLLOP",
        "SCOP",
        "SCOPA",
        "SCOPE",
        "SCOPS",
        "SCOUP",
        "SCOUR",
        "SCOURED",
        "SCOURIE",
        "SHOAL",
        "SHOALS",
        "SHOP",
        "SHOPE",
        "SHOPPE",
        "SHOPS",
        "SHRI",
        "SLOAN",
        "SLOP",
        "SLOPIER",
        "SLUR",
        "SLURP",
        "SOAP",
        "SOAPS",
        "SOCA",
        "SOCAS",
        "SOCS",
        "SOHS",
        "SOLA",
        "SOLAS",
        "SOLO",
        "SOLON",
        "SOON",
        "SOOT",
        "SOOTH",
        "SOOTHS",
        "SOPH",
        "SOPOR",
        "SOPORS",
        "SOPS",
        "SORI",
        "SORN",
        "SORPTION",
        "SORT",
        "SOTH",
        "SOUL",
        "SOUP",
        "SOUPIER",
        "SOUR",
        "SOURED",
        "SPAN",
        "SPEAN",
        "SPEAT",
        "SPET",
        "SPETCH",
        "SPOON",
        "SPOOR",
        "SPOOT",
        "SPORT",
        "SPOSH",
        "SPOT",
        "SPRIT",
        "SPRITE",
        "STOIT",
        "STOOP",
        "STOOPE",
        "STOOR",
        "STROP",
        "STROPHE",
        "TAHA",
        "TANE",
        "TAPE",
        "TAPEN",
        "TAPET",
        "TAPETI",
        "TAPETUM",
        "TATE",
        "TATH",
        "TATU",
        "TAUNT",
        "TAUT",
        "TEAT",
        "TEPA",
        "TETH",
        "THAE",
        "THAN",
        "THANA",
        "THANE",
        "THAT",
        "THETA",
        "THIO",
        "THIR",
        "THIRST",
        "THORN",
        "THORO",
        "THORON",
        "THORP",
        "THORPE",
        "THORPS",
        "THRO",
        "THROE",
        "TIRO",
        "TIROS",
        "TOEA",
        "TOIT",
        "TOON",
        "TOOT",
        "TOOTH",
        "TOOTHS",
        "TOOTHY",
        "TOOTS",
        "TOPE",
        "TOPH",
        "TOPHE",
        "TOPO",
        "TOPOS",
        "TOPS",
        "TORI",
        "TORN",
        "TORO",
        "TOROS",
        "TOROT",
        "TOROTH",
        "TORS",
        "TORSO",
        "TORSOS",
        "TORT",
        "TORTS",
        "TOSH",
        "TOSS",
        "TOST",
        "TRIO",
        "TRIOS",
        "TRITE",
        "TRON",
        "TROOP",
        "TROOPS",
        "TROP",
        "TROPE",
        "TROPPO",
        "TROT",
        "TROTH",
        "TUAN",
        "TUATH",
        "TUNA",
        "TUNE",
        "TYPE",
        "TYPHOON",
        "ULNA",
        "UMAMI",
        "UNAI",
        "UNAIRED",
        "UNAPT",
        "UNCAP",
        "UNCAPE",
        "UNCAPS",
        "UNCO",
        "UNCOPE",
        "UNCOS",
        "UNEATH",
        "UPON",
        "UREDO",
        "YEAH",
        "YEAN",
        "YENTA",
        "YENTE",
        "YTOST"
    ],
    "themeCoords": {
        "PERIOD": [
            [
                0,
                0
            ],
            [
                0,
                1
            ],
            [
                0,
                2
            ],
            [
                1,
                2
            ],
            [
                1,
                1
            ],
            [
                1,
                0
            ]
        ],
        "COMMA": [
            [
                3,
                0
            ],
            [
                2,
                0
            ],
            [
                3,
                1
            ],
            [
                2,
                1
            ],
            [
                2,
                2
            ]
        ],
        "COLON": [
            [
                3,
                4
            ],
            [
                2,
                4
            ],
            [
                1,
                4
            ],
            [
                0,
                4
            ],
            [
                0,
                5
            ]
        ],
        "APOSTROPHE": [
            [
                3,
                3
            ],
            [
                4,
                3
            ],
            [
                4,
                4
            ],
            [
                5,
                4
            ],
            [
                6,
                5
            ],
            [
                6,
                4
            ],
            [
                6,
                3
            ],
            [
                5,
                3
            ],
            [
                4,
                2
            ],
            [
                5,
                2
            ]
        ],
        "HYPHEN": [
            [
                7,
                2
            ],
            [
                7,
                1
            ],
            [
                6,
                1
            ],
            [
                7,
                0
            ],
            [
                6,
                0
            ],
            [
                5,
                0
            ]
        ],
        "SLASH": [
            [
                1,
                5
            ],
            [
                2,
                5
            ],
            [
                3,
                5
            ],
            [
                4,
                5
            ],
            [
                5,
                5
            ]
        ]
    }
}